image_mcp_server/__init__.py
image_mcp_server/api_client.py
image_mcp_server/image_handler.py
image_mcp_server/server.py
image_mcp_server-0.2.3.dist-info/METADATA
image_mcp_server-0.2.3.dist-info/WHEEL
image_mcp_server-0.2.3.dist-info/entry_points.txt
image_mcp_server-0.2.3.dist-info/top_level.txt
image_mcp_server-0.2.3.dist-info/RECORD
