Metadata-Version: 2.4
Name: image-mcp-server
Version: 0.2.3
Summary: 一个简洁的 MCP 服务器，用于图片内容分析，支持本地文件、HTTP URL 和剪贴板图片
Author-email: Your Name <your.email@example.com>
License: MIT
Project-URL: Homepage, https://github.com/yourusername/image-mcp-server
Project-URL: Repository, https://github.com/yourusername/image-mcp-server.git
Project-URL: Issues, https://github.com/yourusername/image-mcp-server/issues
Classifier: Development Status :: 4 - Beta
Classifier: Intended Audience :: Developers
Classifier: License :: OSI Approved :: MIT License
Classifier: Programming Language :: Python :: 3
Classifier: Programming Language :: Python :: 3.12
Requires-Python: >=3.12
Requires-Dist: mcp>=1.0.0
Requires-Dist: httpx[socks]>=0.25.0
Requires-Dist: Pillow>=9.0.0
Requires-Dist: python-dotenv>=1.0.0
Requires-Dist: requests>=2.25.0
Provides-Extra: dev
Requires-Dist: pytest>=7.0.0; extra == "dev"
Requires-Dist: pytest-asyncio>=0.21.0; extra == "dev"
Requires-Dist: black>=23.0.0; extra == "dev"
Requires-Dist: isort>=5.0.0; extra == "dev"
Requires-Dist: mypy>=1.0.0; extra == "dev"
